cobind-1.0.1.data/scripts/cobind.py
cobindability/BED.py
cobindability/__init__.py
cobindability/bbreader.py
cobindability/bw.py
cobindability/coefcal.py
cobindability/findbed.py
cobindability/ireader.py
cobindability/ovbootstrap.py
cobindability/ovstat.py
cobindability/utils.py
cobindability/version.py
cobind-1.0.1.dist-info/LICENSE
cobind-1.0.1.dist-info/METADATA
cobind-1.0.1.dist-info/WHEEL
cobind-1.0.1.dist-info/top_level.txt
cobind-1.0.1.dist-info/RECORD
